[
	{
		"name": "HG001_v",
		"coordinates": [
			37.665936,
			126.736558,
			100
		]
	},
	{
		"name": "HG001",
		"coordinates": [
			37.668229,
			126.724204,
			100
		]
	},
	{
		"name": "HG002",
		"coordinates": [
			37.663351,
			126.721306,
			100
		]
	},
	{
		"name": "HG003",
		"coordinates": [
			37.617674,
			126.797026,
			100
		]
	},
	{
		"name": "HG004",
		"coordinates": [
			37.657212,
			126.740792,
			100
		]
	},
	{
		"name": "HG005",
		"coordinates": [
			37.572388,
			126.804538,
			100
		]
	},
	{
		"name": "HG005_v",
		"coordinates": [
			37.55934,
			126.80551,
			100
		]
	},
	{
		"name": "HG006",
		"coordinates": [
			37.555641,
			126.809915,
			100
		]
	},
	{
		"name": "HG007",
		"coordinates": [
			37.554041,
			126.815306,
			100
		]
	},
	{
		"name": "HG007_JP1",
		"coordinates": [
			37.56554,
			126.85814,
			100
		]
	},
	{
		"name": "HG007_JP2",
		"coordinates": [
			37.551761,
			126.890937,
			100
		]
	},
	{
		"name": "HG007_JP3",
		"coordinates": [
			37.541894,
			126.902695,
			100
		]
	},
	{
		"name": "HG008",
		"coordinates": [
			37.535757,
			126.929511,
			100
		]
	},
	{
		"name": "HG009",
		"coordinates": [
			37.531569,
			126.930601,
			100
		]
	},
	{
		"name": "HG009_v",
		"coordinates": [
			37.525359,
			126.921353,
			100
		]
	},
	{
		"name": "HG010",
		"coordinates": [
			37.524056,
			126.912144,
			100
		]
	},
	{
		"name": "HG011",
		"coordinates": [
			37.522552,
			126.917131,
			100
		]
	}
]